pylocalmem/__init__.py
pylocalmem-1.1.1.dist-info/METADATA
pylocalmem-1.1.1.dist-info/WHEEL
pylocalmem-1.1.1.dist-info/top_level.txt
pylocalmem-1.1.1.dist-info/RECORD
