Metadata-Version: 2.4
Name: Pylocalmem
Version: 1.1.1
Summary: A python package for local process data manipulation
Author: Chasss
Requires-Dist: keystone-engine
Dynamic: author
Dynamic: description
Dynamic: description-content-type
Dynamic: requires-dist
Dynamic: summary
